dsci_prediction/.ipynb_checkpoints/DSCI_prediction-checkpoint.py
dsci_prediction/DSCI_prediction.py
dsci_prediction/__init__.py
dsci_prediction-6.dist-info/LICENSE
dsci_prediction-6.dist-info/WHEEL
dsci_prediction-6.dist-info/METADATA
dsci_prediction-6.dist-info/RECORD
