Metadata-Version: 2.1
Name: dsci-prediction
Version: 6
Summary: a package for predicting if cancer is treatable or not
License: MIT
Author: Clichy Bazenga
Requires-Python: >=3.9,<4.0
Classifier: License :: OSI Approved :: MIT License
Classifier: Programming Language :: Python :: 3
Classifier: Programming Language :: Python :: 3.10
Classifier: Programming Language :: Python :: 3.9
